admin_tools_zinnia-0.1.dist-info/METADATA
admin_tools_zinnia-0.1.dist-info/RECORD
admin_tools_zinnia-0.1.dist-info/WHEEL
admin_tools_zinnia-0.1.dist-info/DESCRIPTION.rst
admin_tools_zinnia-0.1.dist-info/pydist.json
admin_tools_zinnia-0.1.dist-info/top_level.txt
admin_tools_zinnia/__init__.py
admin_tools_zinnia/templates/admin_tools_zinnia/dashboard/modules/linkbacks.html
admin_tools_zinnia/templates/admin_tools_zinnia/dashboard/modules/comments.html
admin_tools_zinnia/templates/admin_tools_zinnia/dashboard/modules/statistics.html
admin_tools_zinnia/templates/admin_tools_zinnia/dashboard/modules/draft_entries.html
admin_tools_zinnia/templates/admin_tools_zinnia/dashboard/modules/quick_entry.html
admin_tools_zinnia/templates/admin/zinnia/app_index.html
admin_tools_zinnia/modules/quick_entry.py
admin_tools_zinnia/modules/__init__.py
admin_tools_zinnia/modules/linkbacks.py
admin_tools_zinnia/modules/statistics.py
admin_tools_zinnia/modules/draft_entries.py
admin_tools_zinnia/modules/comments.py
